smfiles/__init__.py
smfiles/edit.py
smfiles/read.py
smfiles-0.4.dist-info/METADATA
smfiles-0.4.dist-info/WHEEL
smfiles-0.4.dist-info/top_level.txt
smfiles-0.4.dist-info/RECORD
