Metadata-Version: 2.1
Name: smfiles
Version: 0.4
Summary: Read and Edit .sm files and Measure BPM of songs.
Home-page: https://github.com/zhangletao/smfiles
Author: 张乐涛
Author-email: 1668151593@qq.com
License: UNKNOWN
Platform: UNKNOWN
Requires-Dist: librosa
Requires-Dist: numpy
